{
  "brick_id": "667ab81e-3ff0-4fb6-86be-818c8fa5110d",
  "name": "materialFamilyShape",
  "description": "",
  "template_type": "dropdown_iri",
  "namespace": "dpp",
  "target_class": "http://digital-passport.io/concept/materialFamilyShape",
  "leaf_properties": [
    {
      "path": "http://qudt.org/schema/qudt/Unit",
      "label": "value",
      "description": "description for value",
      "min_count": 1,
      "max_count": 1,
      "datatype": null,
      "node_kind": "http://www.w3.org/ns/shacl#IRI",
      "in_values": [
        "http://digital-passport.io/concept/ceramicNonTechnical",
        "http://digital-passport.io/concept/ceramicTechnical",
        "http://digital-passport.io/concept/compositeCeramicMatrix",
        "http://digital-passport.io/concept/compositeMetalMatrix",
        "http://digital-passport.io/concept/compositeNatural",
        "http://digital-passport.io/concept/compositePBCLaminate",
        "http://digital-passport.io/concept/compositePolymerMatrix",
        "http://digital-passport.io/concept/elastomerThermoplasticTPE",
        "http://digital-passport.io/concept/elastomerThermosetRubber",
        "http://digital-passport.io/concept/fluidsGases",
        "http://digital-passport.io/concept/fluidsLiquids",
        "http://digital-passport.io/concept/glassGlassCeramic",
        "http://digital-passport.io/concept/glassTechnical",
        "http://digital-passport.io/concept/metalFerrous",
        "http://digital-passport.io/concept/metalNonFerrous",
        "http://digital-passport.io/concept/metalOther",
        "http://digital-passport.io/concept/metalPrecious",
        "http://digital-passport.io/concept/naturalBiological",
        "http://digital-passport.io/concept/naturalFibers",
        "http://digital-passport.io/concept/naturalWood",
        "http://digital-passport.io/concept/naturalWoodLike",
        "http://digital-passport.io/concept/plasticThermoplasticAmorphous",
        "http://digital-passport.io/concept/plasticThermoplasticSemiCrystalline",
        "http://digital-passport.io/concept/plasticThermoset"
      ],
      "has_value": null,
      "min_inclusive": null,
      "max_inclusive": null,
      "single_line": null,
      "template_type": "dropdown_iri"
    }
  ],
  "xone_alternatives": [],
  "tags": [
    "source:grantami.ttl"
  ],
  "object_type": "NodeShape",
  "properties": {},
  "constraints": [],
  "targets": [],
  "property_path": "",
  "created_at": "",
  "updated_at": "",
  "metadata": {
    "source_iri": "http://digital-passport.io/concept/materialFamilyShape",
    "source_file": "grantami.ttl"
  }
}